dorm.py
dorm-0.4.0.dist-info/LICENSE
dorm-0.4.0.dist-info/METADATA
dorm-0.4.0.dist-info/WHEEL
dorm-0.4.0.dist-info/entry_points.txt
dorm-0.4.0.dist-info/top_level.txt
dorm-0.4.0.dist-info/RECORD
