Metadata-Version: 2.1
Name: dorm
Version: 0.4.0
Summary: A tiny SQLite ORM for Python.
Home-page: https://github.com/dcwatson/dorm
Author: Dan Watson
Author-email: dcwatson@gmail.com
License: MIT
Platform: UNKNOWN
Classifier: Development Status :: 2 - Pre-Alpha
Classifier: Intended Audience :: Developers
Classifier: License :: OSI Approved :: MIT License
Classifier: Programming Language :: Python
Classifier: Programming Language :: Python :: 3
Classifier: Topic :: Database
